[{"model": "webservice.uses", "pk": 1, "fields": {"unique_key": "320ee0fe-8aa6-4f70-9a74-6d46a39766cf", "name": "Automovil"}}, {"model": "webservice.uses", "pk": 2, "fields": {"unique_key": "5ccadc28-a2d4-4e45-9bf6-4d1e99bd2b62", "name": "Moto"}}, {"model": "webservice.uses", "pk": 3, "fields": {"unique_key": "7dfeef51-c084-4c91-b70c-b811a6be75ea", "name": "Transporte"}}, {"model": "webservice.uses", "pk": 4, "fields": {"unique_key": "5422c18e-9e6a-4b77-8b64-add8c0e8d7a6", "name": "Maquinaria Agricola"}}, {"model": "webservice.uses", "pk": 5, "fields": {"unique_key": "db8bb980-2705-48e1-8960-93b58fe9babf", "name": "Maquinaria Vial"}}, {"model": "webservice.uses", "pk": 6, "fields": {"unique_key": "be0b55d4-7c28-4255-b7bd-041280d327e3", "name": "Lancha"}}, {"model": "webservice.uses", "pk": 7, "fields": {"unique_key": "c6ff3a23-e54d-421c-8592-f7263409a991", "name": "Moto Agua"}}, {"model": "webservice.uses", "pk": 8, "fields": {"unique_key": "b89cda91-2657-4d34-945b-164a9acf5220", "name": "Industria"}}]